noble_tls/__init__.py
noble_tls/__version__.py
noble_tls/cookies.py
noble_tls/response.py
noble_tls/sessions.py
noble_tls/c/__init__.py
noble_tls/c/cffi.py
noble_tls/data/tls-client-xgo-1.11.0-linux-amd64.so
noble_tls/exceptions/__init__.py
noble_tls/exceptions/exceptions.py
noble_tls/profiles/__init__.py
noble_tls/profiles/browser_header_orders.json
noble_tls/profiles/example_custom_identifiers.py
noble_tls/profiles/example_usage.py
noble_tls/profiles/profiles.py
noble_tls/profiles/session_factory.py
noble_tls/profiles/test_conversions.py
noble_tls/profiles/data/chrome_137_macos.json
noble_tls/profiles/data/chrome_137_windows.json
noble_tls/profiles/data/edge_136_windows.json
noble_tls/profiles/data/edge_137_windows.json
noble_tls/profiles/data/safari_18.3_ios.json
noble_tls/profiles/data/safari_18.5_ios.json
noble_tls/tests/__init__.py
noble_tls/tests/test_asset.py
noble_tls/tests/test_cffi.py
noble_tls/tests/test_exceptions.py
noble_tls/tests/test_file_fetch.py
noble_tls/tests/test_response.py
noble_tls/tests/test_sessions.py
noble_tls/updater/__init__.py
noble_tls/updater/file_fetch.py
noble_tls/utils/__init__.py
noble_tls/utils/asset.py
noble_tls/utils/custom_identifiers.py
noble_tls/utils/identifiers.py
noble_tls/utils/session_utils.py
noble_tls/utils/structures.py
omar6995_noble_tls-0.1.20.dist-info/licenses/LICENSE
omar6995_noble_tls-0.1.20.dist-info/METADATA
omar6995_noble_tls-0.1.20.dist-info/WHEEL
omar6995_noble_tls-0.1.20.dist-info/top_level.txt
omar6995_noble_tls-0.1.20.dist-info/RECORD
